kiutra_api/__init__.py
kiutra_api/api_client.py
kiutra_api/controller_interfaces.py
kiutra_api/device_interfaces.py
kiutra_api/stream_listener.py
kiutra_api-0.0.4.dist-info/LICENCE.txt
kiutra_api-0.0.4.dist-info/METADATA
kiutra_api-0.0.4.dist-info/WHEEL
kiutra_api-0.0.4.dist-info/top_level.txt
kiutra_api-0.0.4.dist-info/RECORD
